[
  {
    "id": 1745850220238,
    "filename": "Unknown_1745850220204.png",
    "labels": [
      "person"
    ],
    "date": "4/28/2025",
    "time": "4:23:40 PM",
    "filepath": "/uploads/Unknown_1745850220204.png"
  },
  {
    "id": 1745850257192,
    "filename": "Unknown_1745850257187.png",
    "labels": [
      "person"
    ],
    "date": "4/28/2025",
    "time": "4:24:17 PM",
    "filepath": "/uploads/Unknown_1745850257187.png"
  },
  {
    "id": 1745869332884,
    "filename": "Unknown_1745869332881.png",
    "labels": [
      "person"
    ],
    "date": "4/28/2025",
    "time": "9:42:12 PM",
    "filepath": "/uploads/Unknown_1745869332881.png"
  },
  {
    "id": 1745869333831,
    "filename": "Unknown_1745869333828.png",
    "labels": [
      "person"
    ],
    "date": "4/28/2025",
    "time": "9:42:13 PM",
    "filepath": "/uploads/Unknown_1745869333828.png"
  },
  {
    "id": 1745869335490,
    "filename": "Unknown_1745869335486.png",
    "labels": [
      "person"
    ],
    "date": "4/28/2025",
    "time": "9:42:15 PM",
    "filepath": "/uploads/Unknown_1745869335486.png"
  },
  {
    "id": 1745869336652,
    "filename": "Unknown_1745869336649.png",
    "labels": [
      "person"
    ],
    "date": "4/28/2025",
    "time": "9:42:16 PM",
    "filepath": "/uploads/Unknown_1745869336649.png"
  },
  {
    "id": 1745869337857,
    "filename": "Unknown_1745869337854.png",
    "labels": [
      "person"
    ],
    "date": "4/28/2025",
    "time": "9:42:17 PM",
    "filepath": "/uploads/Unknown_1745869337854.png"
  },
  {
    "id": 1745869339024,
    "filename": "Unknown_1745869339020.png",
    "labels": [
      "person"
    ],
    "date": "4/28/2025",
    "time": "9:42:19 PM",
    "filepath": "/uploads/Unknown_1745869339020.png"
  },
  {
    "id": 1745869502516,
    "filename": "Unknown_1745869502514.png",
    "labels": [
      "person"
    ],
    "date": "4/28/2025",
    "time": "9:45:02 PM",
    "filepath": "/uploads/Unknown_1745869502514.png"
  },
  {
    "id": 1745869503174,
    "filename": "Unknown_1745869503172.png",
    "labels": [
      "person"
    ],
    "date": "4/28/2025",
    "time": "9:45:03 PM",
    "filepath": "/uploads/Unknown_1745869503172.png"
  },
  {
    "id": 1745872595262,
    "filename": "Unknown_1745872595260.png",
    "labels": [
      "person"
    ],
    "date": "4/28/2025",
    "time": "10:36:35 PM",
    "filepath": "/uploads/Unknown_1745872595260.png"
  },
  {
    "id": 1745872599935,
    "filename": "Unknown_1745872599932.png",
    "labels": [
      "cell phone"
    ],
    "date": "4/28/2025",
    "time": "10:36:39 PM",
    "filepath": "/uploads/Unknown_1745872599932.png"
  },
  {
    "id": 1745915743584,
    "filename": "Unknown_1745915743582.png",
    "labels": [
      "No Detection"
    ],
    "date": "4/29/2025",
    "time": "10:35:43 AM",
    "filepath": "/uploads/Unknown_1745915743582.png"
  },
  {
    "id": 1745915744493,
    "filename": "Unknown_1745915744488.png",
    "labels": [
      "No Detection"
    ],
    "date": "4/29/2025",
    "time": "10:35:44 AM",
    "filepath": "/uploads/Unknown_1745915744488.png"
  }
]